anonymized_fraud_detection/__init__.py
anonymized_fraud_detection/predict.py
anonymized_fraud_detection/train.py
anonymized_fraud_detection/utilities/__init__.py
anonymized_fraud_detection/utilities/analytical_reporting_functions.py
anonymized_fraud_detection/utilities/models.py
anonymized_fraud_detection/utilities/util_functions.py
anonymized_fraud_detection-0.1.3.dist-info/LICENSE
anonymized_fraud_detection-0.1.3.dist-info/METADATA
anonymized_fraud_detection-0.1.3.dist-info/WHEEL
anonymized_fraud_detection-0.1.3.dist-info/top_level.txt
anonymized_fraud_detection-0.1.3.dist-info/RECORD
